mahiro/__init__.py
mahiro/main.py
mahiro/models.py
mahiro/send.py
mahiro/version.py
mahiro-1.5.0.dist-info/LICENSE
mahiro-1.5.0.dist-info/METADATA
mahiro-1.5.0.dist-info/WHEEL
mahiro-1.5.0.dist-info/top_level.txt
mahiro-1.5.0.dist-info/RECORD
